<?xml version="1.0"?>
<Results version="1.0">
<ReportNode type="testrun">
<ReportNode type="Iteration">
<ReportNode type="Action">
<ReportNode type="Step">
<Data>
    <Name>Name redefined</Name>
    <ErrorText>Name redefined</ErrorText>
    <Description>&lt;BR/&gt;Line (51): &amp;quot;Dim x,y&amp;quot;.</Description>
    <StartTime>2019-09-16 11:30:26</StartTime>
    <Result>Failed</Result>
    <Extension>
      <IconKey>e254c9e0a01f4f889fe6d1b24f0840fd</IconKey>
      <IsPlainTextNodeName>True</IsPlainTextNodeName>
      <MergeIsErrorIcon>True</MergeIsErrorIcon>
    </Extension>
  </Data>
</ReportNode>
<ReportNode type="Step">
<Data>
    <Name>Stop Run</Name>
    <Description>Run stopped by user.</Description>
    <StartTime>2019-09-16 11:30:28</StartTime>
    <Result>Information</Result>
    <Extension>
      <IconKey>9aed7add4a0940bea451f3b93d52dfe9</IconKey>
      <IsPlainTextNodeName>True</IsPlainTextNodeName>
    </Extension>
  </Data>
</ReportNode>
<Data>
    <Name>Action1</Name>
    <Description />
    <StartTime>2019-09-16 11:30:26</StartTime>
    <Duration>2</Duration>
    <Result>Failed</Result>
    <InputParameters />
    <Extension>
      <IconKey>913726c7f69946a582671a3387a3c964</IconKey>
      <IsPlainTextNodeName>True</IsPlainTextNodeName>
    </Extension>
  </Data>
</ReportNode>
<Data>
    <Name>Action0</Name>
    <Description />
    <StartTime>2019-09-16 11:30:26</StartTime>
    <Duration>2</Duration>
    <Result>Failed</Result>
    <Extension>
      <IconKey>8eaf6bb072f14a7c81e1aac9daf27691</IconKey>
      <IsPlainTextNodeName>True</IsPlainTextNodeName>
    </Extension>
    <Index>1</Index>
    <TestedApplications />
  </Data>
</ReportNode>
<Data>
    <Name>conditional</Name>
    <ToolName>HPE Unified Functional Testing</ToolName>
    <ToolVersion>14.02</ToolVersion>
    <Description />
    <StartTime>2019-09-16 11:30:25</StartTime>
    <Duration>3</Duration>
    <Result>Failed</Result>
    <InputParameters />
    <Extension>
      <IconKey>05af58352326429db368d73c38380d3a</IconKey>
      <IsPlainTextNodeName>True</IsPlainTextNodeName>
    </Extension>
    <Environment>
      <Timezone>+05:30:00</Timezone>
      <Locale>English (United States)</Locale>
      <User>DIR\PDC3A-Training.PDC3A</User>
      <CpuInfo>Intel(R) Core(TM) i3-6100T CPU @ 3.20GHz</CpuInfo>
      <NumberOfCores>4</NumberOfCores>
      <TotalMemory>8076</TotalMemory>
      <HostName>dir.svc.accenture.com\P3A-HYCQXJ2</HostName>
      <OSInfo>Windows 10</OSInfo>
    </Environment>
    <TestedApplications />
    <Links>
      <Link type="DataTable" reference="Default.xls" displayname="Default Data Table" />
    </Links>
  </Data>
</ReportNode>
<GeneralInfo>
    <ResultName>Res12</ResultName>
    <RunStartTime>2019-09-16 11:30:25</RunStartTime>
    <Timezone>+05:30:00</Timezone>
    <OrchestrationToolName>HPE Unified Functional Testing</OrchestrationToolName>
    <OrchestrationToolVersion>14.02</OrchestrationToolVersion>
  </GeneralInfo>
</Results>